{
  "schema_version": "1.0",
  "generated_at": "2026-07-03T17:39:51+09:00",
  "backtest": {
    "period_days": 240,
    "universe": "관심종목",
    "universe_count": 15,
    "hold_bars": 2,
    "score_cutoff": 55,
    "overall": {
      "signals": 2604,
      "filled": 1682,
      "no_fill": 922,
      "hit_target1": 247,
      "hit_target2": 209,
      "hit_stop": 213,
      "timecut": 1013,
      "win_rate": 52.1,
      "target_hit_rate": 27.1,
      "avg_r": 0.06
    },
    "by_score": {
      "55-64": {
        "signals": 360,
        "filled": 208,
        "no_fill": 152,
        "hit_target1": 22,
        "hit_target2": 14,
        "hit_stop": 34,
        "timecut": 138,
        "win_rate": 47.1,
        "target_hit_rate": 17.3,
        "avg_r": -0.01
      },
      "65-74": {
        "signals": 380,
        "filled": 207,
        "no_fill": 173,
        "hit_target1": 31,
        "hit_target2": 23,
        "hit_stop": 24,
        "timecut": 129,
        "win_rate": 52.2,
        "target_hit_rate": 26.1,
        "avg_r": 0.12
      },
      "75+": {
        "signals": 1864,
        "filled": 1267,
        "no_fill": 597,
        "hit_target1": 194,
        "hit_target2": 172,
        "hit_stop": 155,
        "timecut": 746,
        "win_rate": 52.9,
        "target_hit_rate": 28.9,
        "avg_r": 0.06
      }
    },
    "by_entry_type": {
      "now": {
        "signals": 714,
        "filled": 714,
        "no_fill": 0,
        "hit_target1": 121,
        "hit_target2": 101,
        "hit_stop": 97,
        "timecut": 395,
        "win_rate": 52.5,
        "target_hit_rate": 31.1,
        "avg_r": 0.07
      },
      "breakout": {
        "signals": 1890,
        "filled": 968,
        "no_fill": 922,
        "hit_target1": 126,
        "hit_target2": 108,
        "hit_stop": 116,
        "timecut": 618,
        "win_rate": 51.8,
        "target_hit_rate": 24.2,
        "avg_r": 0.05
      }
    },
    "by_regime": {
      "상승": {
        "signals": 2045,
        "filled": 1320,
        "no_fill": 725,
        "hit_target1": 204,
        "hit_target2": 191,
        "hit_stop": 165,
        "timecut": 760,
        "win_rate": 54.7,
        "target_hit_rate": 29.9,
        "avg_r": 0.08
      },
      "하락": {
        "signals": 354,
        "filled": 243,
        "no_fill": 111,
        "hit_target1": 34,
        "hit_target2": 12,
        "hit_stop": 36,
        "timecut": 161,
        "win_rate": 42.4,
        "target_hit_rate": 18.9,
        "avg_r": -0.0
      },
      "횡보": {
        "signals": 205,
        "filled": 119,
        "no_fill": 86,
        "hit_target1": 9,
        "hit_target2": 6,
        "hit_stop": 12,
        "timecut": 92,
        "win_rate": 42.9,
        "target_hit_rate": 12.6,
        "avg_r": -0.04
      }
    },
    "regime_method": "KOSPI(^KS11) 20일 이동평균 기준 국면 분류: 종가>MA20×1.005='상승', 종가<MA20×0.995='하락', 나머지='횡보'. 결측일='횡보'. KOSPI 미확보 시 by_regime 전 버킷 빈 집계.",
    "by_exit_speed": {
      "1일차": {
        "signals": 157,
        "filled": 157,
        "no_fill": 0,
        "hit_target1": 0,
        "hit_target2": 82,
        "hit_stop": 75,
        "timecut": 0,
        "win_rate": 50.3,
        "target_hit_rate": 52.2,
        "avg_r": 0.0
      },
      "2일차": {
        "signals": 512,
        "filled": 512,
        "no_fill": 0,
        "hit_target1": 247,
        "hit_target2": 127,
        "hit_stop": 138,
        "timecut": 0,
        "win_rate": 73.0,
        "target_hit_rate": 73.0,
        "avg_r": 0.32
      },
      "시간청산": {
        "signals": 1013,
        "filled": 1013,
        "no_fill": 0,
        "hit_target1": 0,
        "hit_target2": 0,
        "hit_stop": 0,
        "timecut": 1013,
        "win_rate": 41.8,
        "target_hit_rate": 0.0,
        "avg_r": -0.06
      }
    },
    "exit_speed_note": "★일봉 기준(분·시간 단위 보유시간 불가). '1일차'/'2일차'=목표·손절 청산까지 소요 거래일(봉) 수. '시간청산'=보유창(2거래일) 전체 경과 후 마지막 종가로 청산.",
    "diagnostics": [
      "시간청산이 60%로 많아요 — 목표가가 멀거나 보유 기간이 짧을 수 있어요."
    ],
    "note": "과거 일봉에 현 규칙을 적용한 백테스트(미국증시 환경 보정 제외). 관리정책 반영: 목표1에서 절반 익절 + 목표1 후 손절을 본전으로 이동. 한 봉 내 손절을 목표보다 먼저 보는 보수적 판정. 실측 가격만 사용."
  },
  "tuning": {
    "current": {
      "stop_mult": 1.5,
      "target1_mult": 2.0,
      "target2_mult": 3.0,
      "score_cutoff": 55
    },
    "suggestion": null,
    "method": "train 70% / val 30% 시간 분할 · val 평균 R 최대 + 현재 대비 +0.05R(구간별 +0.08R) 이상일 때만 제안(과최적화 방지). 관리정책(목표1 절반익절·본전스톱) 반영. 적용은 사용자 승인.",
    "note": "지금 설정이 검증구간에서 가장 무난해요 — 바꿀 만한 보정안이 없어요.",
    "by_bucket": {},
    "by_bucket_note": "점수 구간별로 손절·목표를 따로 학습한 결과입니다. 표본이 충분하고 개선이 뚜렷한 구간만 제안돼요."
  },
  "applied_tuning": {
    "stop_mult": 1.5,
    "target1_mult": 2.0,
    "target2_mult": 3.0,
    "score_cutoff": 55,
    "risk_per_trade_pct": 2.0,
    "max_weight_pct": 15.0,
    "min_weight_pct": 3.0,
    "partial_t1_frac": 0.5,
    "breakeven_after_t1": 1.0
  },
  "forward": {
    "status": "ok",
    "matured": 533,
    "logged": 682,
    "agg": {
      "signals": 533,
      "filled": 415,
      "no_fill": 118,
      "hit_target1": 51,
      "hit_target2": 26,
      "hit_stop": 124,
      "timecut": 214,
      "win_rate": 40.2,
      "target_hit_rate": 18.6,
      "avg_r": -0.2
    }
  },
  "disclaimer": "통계는 과거·실거래 실측 기반 참고용이며 미래 수익을 보장하지 않습니다.",
  "learned_weights": {
    "current": {
      "base": 50,
      "align_up": 18,
      "above_ma20": 8,
      "vol_surge": 15,
      "vol_ok": 7,
      "vol_dry": -8,
      "strong_close": 14,
      "weak_close": -12,
      "rsi_up": 13,
      "rsi_hot": -10,
      "rsi_oversold": 4,
      "breakout": 14,
      "mom_up": 8,
      "gap_up": 0,
      "gap_down": 0,
      "vol_accel": 0,
      "streak_up": 0,
      "near_high": 0,
      "range_exp": 0,
      "ma20_up": 0,
      "for_buy": 0,
      "for_sell": 0,
      "org_buy": 0,
      "org_sell": 0,
      "align_down": -8
    },
    "labels": {
      "align_up": "정배열(MA5>MA20)",
      "above_ma20": "현재가 > 20일선",
      "vol_surge": "거래량 급증(≥1.5x)",
      "vol_ok": "거래량 양호(≥1.0x)",
      "vol_dry": "거래량 위축(<0.6x)",
      "strong_close": "강세 마감(종가위치≥60%)",
      "weak_close": "윗꼬리/분배(<30%)",
      "rsi_up": "RSI 상승(50~70)",
      "rsi_hot": "RSI 과열(>75)",
      "rsi_oversold": "RSI 침체(<35)",
      "breakout": "변동성 돌파 상회",
      "mom_up": "5일 모멘텀 양(+)",
      "gap_up": "시가 갭상승(≥1%)",
      "gap_down": "시가 갭하락(≤-1%)",
      "vol_accel": "거래대금 가속(5d≥1.2×20d)",
      "streak_up": "연속 양봉(3일+)",
      "near_high": "20일 전고점 근접(≥98%)",
      "range_exp": "장대봉(범위≥1.5×ATR)",
      "ma20_up": "MA20 상승추세",
      "for_buy": "외국인 순매수",
      "for_sell": "외국인 순매도",
      "org_buy": "기관 순매수",
      "org_sell": "기관 순매도",
      "align_down": "역배열(MA5<MA20)"
    },
    "features": [
      "align_up",
      "above_ma20",
      "vol_surge",
      "vol_ok",
      "vol_dry",
      "strong_close",
      "weak_close",
      "rsi_up",
      "rsi_hot",
      "rsi_oversold",
      "breakout",
      "mom_up",
      "gap_up",
      "gap_down",
      "vol_accel",
      "streak_up",
      "near_high",
      "range_exp",
      "ma20_up",
      "for_buy",
      "for_sell",
      "org_buy",
      "org_sell"
    ],
    "suggestion": {
      "base": 50,
      "align_up": -6,
      "above_ma20": 2,
      "vol_surge": -4,
      "vol_ok": -6,
      "vol_dry": -10,
      "strong_close": 1,
      "weak_close": -3,
      "rsi_up": -2,
      "rsi_hot": 7,
      "rsi_oversold": -1,
      "breakout": -5,
      "mom_up": 7,
      "gap_up": 7,
      "gap_down": 3,
      "vol_accel": 3,
      "streak_up": 7,
      "near_high": 5,
      "range_exp": 8,
      "ma20_up": -3,
      "for_buy": 12,
      "for_sell": 7,
      "org_buy": 18,
      "org_sell": 15,
      "align_down": 0,
      "val_auc": 0.533,
      "current_val_auc": 0.533,
      "basis": "학습은 했지만 검증 성능 개선이 작아요(AUC 0.533→0.533). 참고용으로만 보고, 적용은 신중히 — 표본이 더 쌓이면 정확해져요."
    },
    "method": "과거 일봉의 '지표→48h 승패'를 로지스틱 회귀로 학습(numpy). train 70%/val 30% 시간분할 · 검증 AUC 가 현재 규칙보다 +0.02 이상 좋을 때만 제안(과최적화 방지). 적용은 사용자 승인.",
    "disclaimer": "학습 가중치는 과거 데이터 기반 확률 추정(베타)이며 미래 수익을 보장하지 않습니다.",
    "metrics": {
      "train_n": 31469,
      "val_n": 13487,
      "win_base_rate": 48.5,
      "current_val_auc": 0.533,
      "learned_val_auc": 0.533
    },
    "recommended": false,
    "generated_at": "2026-07-03T17:40:21+09:00",
    "sample_count": 44956,
    "applied": false
  },
  "winrate_combos": {
    "generated_at": "2026-07-03T17:40:21+09:00",
    "base_winrate": 0.485,
    "n_total": 44956,
    "n_combos": 58,
    "min_sample": 120,
    "method": "과거 일봉의 (점수구간 × 거래량 × 외국인순매매 × 기관순매매) 조합별 48h 승률·평균R·payoff. 표본 120건 미만 조합은 우연 방지로 제외.",
    "disclaimer": "과거 데이터 기반 참고치이며 미래 수익을 보장하지 않습니다. 조합을 좁힐수록 표본이 줄어 신뢰가 낮아집니다. 호가 매수/매도 비율은 과거 기록이 없어 제외(향후 적재 예정).",
    "best": [
      {
        "score": "75+",
        "volume": "급증(≥1.5x)",
        "foreign": "순매수",
        "inst": "순매수",
        "winrate": 0.579,
        "n": 1847,
        "lift": 0.094,
        "avg_r": 0.11,
        "payoff": 1.14
      },
      {
        "score": "55-64",
        "volume": "양호(1~1.5x)",
        "foreign": "순매수",
        "inst": "순매도",
        "winrate": 0.575,
        "n": 127,
        "lift": 0.09,
        "avg_r": 0.18,
        "payoff": 1.3
      },
      {
        "score": "65-74",
        "volume": "보통(0.6~1x)",
        "foreign": "순매수",
        "inst": "순매수",
        "winrate": 0.57,
        "n": 251,
        "lift": 0.085,
        "avg_r": 0.14,
        "payoff": 1.28
      },
      {
        "score": "55-64",
        "volume": "위축(<0.6x)",
        "foreign": "순매수",
        "inst": "순매수",
        "winrate": 0.56,
        "n": 134,
        "lift": 0.075,
        "avg_r": 0.16,
        "payoff": 1.35
      },
      {
        "score": "75+",
        "volume": "급증(≥1.5x)",
        "foreign": "순매도",
        "inst": "순매수",
        "winrate": 0.553,
        "n": 1160,
        "lift": 0.069,
        "avg_r": 0.08,
        "payoff": 1.11
      },
      {
        "score": "75+",
        "volume": "급증(≥1.5x)",
        "foreign": "순매수",
        "inst": "순매도",
        "winrate": 0.549,
        "n": 902,
        "lift": 0.064,
        "avg_r": 0.06,
        "payoff": 1.03
      },
      {
        "score": "65-74",
        "volume": "위축(<0.6x)",
        "foreign": "순매수",
        "inst": "순매도",
        "winrate": 0.545,
        "n": 264,
        "lift": 0.061,
        "avg_r": 0.19,
        "payoff": 1.46
      },
      {
        "score": "75+",
        "volume": "양호(1~1.5x)",
        "foreign": "순매수",
        "inst": "순매수",
        "winrate": 0.544,
        "n": 1391,
        "lift": 0.059,
        "avg_r": 0.1,
        "payoff": 1.28
      },
      {
        "score": "<55",
        "volume": "보통(0.6~1x)",
        "foreign": "순매수",
        "inst": "순매수",
        "winrate": 0.541,
        "n": 196,
        "lift": 0.056,
        "avg_r": 0.14,
        "payoff": 1.46
      },
      {
        "score": "75+",
        "volume": "보통(0.6~1x)",
        "foreign": "순매수",
        "inst": "순매수",
        "winrate": 0.538,
        "n": 1515,
        "lift": 0.053,
        "avg_r": 0.08,
        "payoff": 1.18
      }
    ],
    "worst": [
      {
        "score": "65-74",
        "volume": "위축(<0.6x)",
        "foreign": "중립",
        "inst": "중립",
        "winrate": 0.343,
        "n": 677,
        "lift": -0.142,
        "avg_r": -0.17,
        "payoff": 1.09
      },
      {
        "score": "<55",
        "volume": "보통(0.6~1x)",
        "foreign": "중립",
        "inst": "중립",
        "winrate": 0.413,
        "n": 1882,
        "lift": -0.072,
        "avg_r": -0.03,
        "payoff": 1.03
      },
      {
        "score": "65-74",
        "volume": "양호(1~1.5x)",
        "foreign": "중립",
        "inst": "중립",
        "winrate": 0.419,
        "n": 258,
        "lift": -0.066,
        "avg_r": -0.03,
        "payoff": 1.16
      }
    ],
    "table": {
      "75+|보통(0.6~1x)|중립|중립": {
        "winrate": 0.437,
        "n": 3403,
        "lift": -0.048,
        "avg_r": -0.04
      },
      "75+|양호(1~1.5x)|중립|중립": {
        "winrate": 0.43,
        "n": 2565,
        "lift": -0.055,
        "avg_r": -0.03
      },
      "65-74|위축(<0.6x)|중립|중립": {
        "winrate": 0.343,
        "n": 677,
        "lift": -0.142,
        "avg_r": -0.17
      },
      "75+|위축(<0.6x)|중립|중립": {
        "winrate": 0.427,
        "n": 1350,
        "lift": -0.058,
        "avg_r": -0.03
      },
      "65-74|보통(0.6~1x)|중립|중립": {
        "winrate": 0.45,
        "n": 1115,
        "lift": -0.035,
        "avg_r": -0.05
      },
      "55-64|위축(<0.6x)|중립|중립": {
        "winrate": 0.425,
        "n": 683,
        "lift": -0.06,
        "avg_r": -0.07
      },
      "<55|위축(<0.6x)|중립|중립": {
        "winrate": 0.421,
        "n": 1993,
        "lift": -0.064,
        "avg_r": -0.07
      },
      "65-74|양호(1~1.5x)|중립|중립": {
        "winrate": 0.419,
        "n": 258,
        "lift": -0.066,
        "avg_r": -0.03
      },
      "75+|급증(≥1.5x)|중립|중립": {
        "winrate": 0.471,
        "n": 2104,
        "lift": -0.014,
        "avg_r": -0.01
      },
      "<55|보통(0.6~1x)|중립|중립": {
        "winrate": 0.413,
        "n": 1882,
        "lift": -0.072,
        "avg_r": -0.03
      },
      "<55|양호(1~1.5x)|중립|중립": {
        "winrate": 0.422,
        "n": 561,
        "lift": -0.062,
        "avg_r": -0.1
      },
      "55-64|보통(0.6~1x)|중립|중립": {
        "winrate": 0.46,
        "n": 997,
        "lift": -0.025,
        "avg_r": -0.01
      },
      "55-64|양호(1~1.5x)|중립|중립": {
        "winrate": 0.469,
        "n": 192,
        "lift": -0.016,
        "avg_r": 0.08
      },
      "<55|급증(≥1.5x)|중립|중립": {
        "winrate": 0.464,
        "n": 125,
        "lift": -0.021,
        "avg_r": -0.07
      },
      "<55|보통(0.6~1x)|순매도|순매도": {
        "winrate": 0.507,
        "n": 641,
        "lift": 0.022,
        "avg_r": 0.1
      },
      "55-64|보통(0.6~1x)|순매수|순매도": {
        "winrate": 0.508,
        "n": 533,
        "lift": 0.024,
        "avg_r": 0.11
      },
      "75+|보통(0.6~1x)|순매도|순매수": {
        "winrate": 0.509,
        "n": 1757,
        "lift": 0.024,
        "avg_r": 0.06
      },
      "<55|양호(1~1.5x)|순매도|순매도": {
        "winrate": 0.473,
        "n": 207,
        "lift": -0.011,
        "avg_r": 0.01
      },
      "<55|보통(0.6~1x)|순매도|순매수": {
        "winrate": 0.507,
        "n": 458,
        "lift": 0.022,
        "avg_r": 0.07
      },
      "75+|양호(1~1.5x)|순매도|순매수": {
        "winrate": 0.518,
        "n": 1418,
        "lift": 0.033,
        "avg_r": 0.09
      },
      "<55|보통(0.6~1x)|순매수|순매도": {
        "winrate": 0.506,
        "n": 782,
        "lift": 0.021,
        "avg_r": 0.06
      },
      "65-74|보통(0.6~1x)|순매도|순매수": {
        "winrate": 0.522,
        "n": 345,
        "lift": 0.037,
        "avg_r": 0.06
      },
      "<55|양호(1~1.5x)|순매수|순매도": {
        "winrate": 0.534,
        "n": 253,
        "lift": 0.049,
        "avg_r": 0.04
      },
      "<55|위축(<0.6x)|순매수|순매수": {
        "winrate": 0.521,
        "n": 261,
        "lift": 0.036,
        "avg_r": 0.1
      },
      "<55|보통(0.6~1x)|순매수|순매수": {
        "winrate": 0.541,
        "n": 196,
        "lift": 0.056,
        "avg_r": 0.14
      },
      "<55|위축(<0.6x)|순매도|순매도": {
        "winrate": 0.492,
        "n": 765,
        "lift": 0.007,
        "avg_r": 0.07
      },
      "55-64|보통(0.6~1x)|순매도|순매수": {
        "winrate": 0.531,
        "n": 288,
        "lift": 0.046,
        "avg_r": 0.1
      },
      "65-74|위축(<0.6x)|순매수|순매도": {
        "winrate": 0.545,
        "n": 264,
        "lift": 0.061,
        "avg_r": 0.19
      },
      "<55|위축(<0.6x)|순매도|순매수": {
        "winrate": 0.488,
        "n": 562,
        "lift": 0.003,
        "avg_r": 0.05
      },
      "55-64|보통(0.6~1x)|순매도|순매도": {
        "winrate": 0.499,
        "n": 347,
        "lift": 0.014,
        "avg_r": 0.09
      },
      "75+|양호(1~1.5x)|순매수|순매수": {
        "winrate": 0.544,
        "n": 1391,
        "lift": 0.059,
        "avg_r": 0.1
      },
      "65-74|보통(0.6~1x)|순매수|순매도": {
        "winrate": 0.51,
        "n": 447,
        "lift": 0.025,
        "avg_r": 0.07
      },
      "75+|급증(≥1.5x)|순매도|순매도": {
        "winrate": 0.463,
        "n": 281,
        "lift": -0.022,
        "avg_r": -0.01
      },
      "<55|위축(<0.6x)|순매수|순매도": {
        "winrate": 0.465,
        "n": 795,
        "lift": -0.02,
        "avg_r": 0.03
      },
      "55-64|위축(<0.6x)|순매도|순매수": {
        "winrate": 0.508,
        "n": 248,
        "lift": 0.023,
        "avg_r": 0.04
      },
      "75+|급증(≥1.5x)|순매수|순매도": {
        "winrate": 0.549,
        "n": 902,
        "lift": 0.064,
        "avg_r": 0.06
      },
      "75+|급증(≥1.5x)|순매도|순매수": {
        "winrate": 0.553,
        "n": 1160,
        "lift": 0.069,
        "avg_r": 0.08
      },
      "75+|보통(0.6~1x)|순매수|순매수": {
        "winrate": 0.538,
        "n": 1515,
        "lift": 0.053,
        "avg_r": 0.08
      },
      "75+|급증(≥1.5x)|순매수|순매수": {
        "winrate": 0.579,
        "n": 1847,
        "lift": 0.094,
        "avg_r": 0.11
      },
      "75+|양호(1~1.5x)|순매수|순매도": {
        "winrate": 0.536,
        "n": 1269,
        "lift": 0.051,
        "avg_r": 0.08
      },
      "65-74|양호(1~1.5x)|순매수|순매도": {
        "winrate": 0.514,
        "n": 146,
        "lift": 0.029,
        "avg_r": 0.09
      },
      "75+|양호(1~1.5x)|순매도|순매도": {
        "winrate": 0.538,
        "n": 468,
        "lift": 0.054,
        "avg_r": 0.14
      },
      "75+|보통(0.6~1x)|순매수|순매도": {
        "winrate": 0.534,
        "n": 1638,
        "lift": 0.049,
        "avg_r": 0.09
      },
      "55-64|위축(<0.6x)|순매수|순매수": {
        "winrate": 0.56,
        "n": 134,
        "lift": 0.075,
        "avg_r": 0.16
      },
      "65-74|보통(0.6~1x)|순매도|순매도": {
        "winrate": 0.496,
        "n": 238,
        "lift": 0.011,
        "avg_r": 0.18
      },
      "75+|보통(0.6~1x)|순매도|순매도": {
        "winrate": 0.496,
        "n": 689,
        "lift": 0.011,
        "avg_r": 0.09
      },
      "75+|위축(<0.6x)|순매도|순매수": {
        "winrate": 0.495,
        "n": 529,
        "lift": 0.01,
        "avg_r": 0.12
      },
      "55-64|위축(<0.6x)|순매도|순매도": {
        "winrate": 0.51,
        "n": 194,
        "lift": 0.025,
        "avg_r": 0.13
      },
      "65-74|보통(0.6~1x)|순매수|순매수": {
        "winrate": 0.57,
        "n": 251,
        "lift": 0.085,
        "avg_r": 0.14
      },
      "65-74|위축(<0.6x)|순매수|순매수": {
        "winrate": 0.514,
        "n": 146,
        "lift": 0.029,
        "avg_r": 0.13
      },
      "55-64|위축(<0.6x)|순매수|순매도": {
        "winrate": 0.461,
        "n": 280,
        "lift": -0.024,
        "avg_r": 0.03
      },
      "65-74|위축(<0.6x)|순매도|순매수": {
        "winrate": 0.498,
        "n": 235,
        "lift": 0.013,
        "avg_r": 0.11
      },
      "55-64|보통(0.6~1x)|순매수|순매수": {
        "winrate": 0.483,
        "n": 211,
        "lift": -0.002,
        "avg_r": 0.05
      },
      "75+|위축(<0.6x)|순매수|순매도": {
        "winrate": 0.524,
        "n": 504,
        "lift": 0.039,
        "avg_r": 0.1
      },
      "75+|위축(<0.6x)|순매수|순매수": {
        "winrate": 0.46,
        "n": 439,
        "lift": -0.025,
        "avg_r": 0.04
      },
      "65-74|위축(<0.6x)|순매도|순매도": {
        "winrate": 0.453,
        "n": 172,
        "lift": -0.031,
        "avg_r": 0.07
      },
      "75+|위축(<0.6x)|순매도|순매도": {
        "winrate": 0.465,
        "n": 340,
        "lift": -0.02,
        "avg_r": 0.08
      },
      "55-64|양호(1~1.5x)|순매수|순매도": {
        "winrate": 0.575,
        "n": 127,
        "lift": 0.09,
        "avg_r": 0.18
      }
    }
  }
}
